gator/__init__.py
gator/main.py
gator/auth/__init__.py
gator/auth/auth_commands.py
gator/auth/credentials.py
gator/cli/__init__.py
gator/cli/functions_cli.py
gator/cli/storage_cli.py
gator/custom/__init__.py
gator/custom/custom_cli.py
gator/modules/__init__.py
gator/modules/functions/__init__.py
gator/modules/functions/functions.py
gator/modules/functions/permissions.py
gator/modules/functions/triggers.py
gator/modules/storage/__init__.py
gator/modules/storage/buckets.py
gator/modules/storage/permissions.py
gator/utils/__init__.py
gator/utils/print_helpers.py
gator/utils/version_check.py
gator_red-0.6.2.2.1.dist-info/LICENSE
gator_red-0.6.2.2.1.dist-info/METADATA
gator_red-0.6.2.2.1.dist-info/WHEEL
gator_red-0.6.2.2.1.dist-info/entry_points.txt
gator_red-0.6.2.2.1.dist-info/top_level.txt
gator_red-0.6.2.2.1.dist-info/RECORD
