Metadata-Version: 2.1
Name: gator-red
Version: 0.6.2.2.1
License-File: LICENSE
Requires-Dist: cachetools (==5.3.1)
Requires-Dist: certifi (==2023.7.22)
Requires-Dist: charset-normalizer (==3.2.0)
Requires-Dist: click (==8.1.6)
Requires-Dist: colorama (==0.4.6)
Requires-Dist: google-api-core (==2.11.1)
Requires-Dist: google-api-python-client (==2.95.0)
Requires-Dist: google-auth (==2.22.0)
Requires-Dist: google-auth-httplib2 (==0.1.0)
Requires-Dist: googleapis-common-protos (==1.60.0)
Requires-Dist: httplib2 (==0.22.0)
Requires-Dist: idna (==3.4)
Requires-Dist: protobuf (==4.23.4)
Requires-Dist: pyasn1 (==0.5.0)
Requires-Dist: pyasn1-modules (==0.3.0)
Requires-Dist: pyparsing (==3.1.1)
Requires-Dist: requests (==2.31.0)
Requires-Dist: rsa (==4.9)
Requires-Dist: six (==1.16.0)
Requires-Dist: termcolor (==2.3.0)
Requires-Dist: uritemplate (==4.1.1)
Requires-Dist: urllib3 (==1.26.16)
